amz/__init__.py
amz/init.py
amz/install.py
amz/loading.py
amz/meta.py
amz/processor.py
amz/config/amz-config.yaml
amz/config/amz_source.sh
amz/data/VERSION
amz/data/amz_env.sh
amz/data/auto_update/amz_update.py
amz/data/auto_update/amz_updater.service
amz/data/auto_update/amz_updater.timer
amz/data/githooks/config/.clang-format
amz/data/githooks/config/.pre-commit-config.yaml
amz/data/githooks/config/.pylintrc
amz/data/githooks/config/.style.yapf
amz/data/githooks/config/CPPLINT.cfg
amz/data/githooks/scripts/check_copyright.py
amz/data/githooks/scripts/check_python_shebang.py
amz/data/githooks/scripts/pylint_mw.py
amz/data/githooks/scripts/yapf_mw.py
amz/data/misc/installscript_sample.yaml
amz/data/misc/samples/osqp.yaml
amz/data/misc/samples/ros.yaml
amz_tool-2021.5.1.data/scripts/amz
amz_tool-2021.5.1.dist-info/METADATA
amz_tool-2021.5.1.dist-info/WHEEL
amz_tool-2021.5.1.dist-info/top_level.txt
amz_tool-2021.5.1.dist-info/RECORD
